README.md
setup.cfg
setup.py
distributionsYAKS/Binomialdistribution.py
distributionsYAKS/Gaussiandistribution.py
distributionsYAKS/Generaldistribution.py
distributionsYAKS/__init__.py
distributionsYAKS.egg-info/PKG-INFO
distributionsYAKS.egg-info/SOURCES.txt
distributionsYAKS.egg-info/dependency_links.txt
distributionsYAKS.egg-info/not-zip-safe
distributionsYAKS.egg-info/top_level.txt